ars/__init__.py
ars/adventure.py
ars/adventure_integration.py
ars/character.py
ars/cli.py
ars/combat.py
ars/commands/__init__.py
ars/commands/adventure_commands.py
ars/commands/character_wizard.py
ars/commands/combat_commands.py
ars/commands/covenant_commands.py
ars/commands/economy_commands.py
ars/commands/lab_commands.py
ars/commands/magic_item_commands.py
ars/commands/research_commands.py
ars/commands/season_commands.py
ars/commands/spell_commands.py
ars/commands/vis_aura_commands.py
ars/covenant.py
ars/covenant_display.py
ars/covenant_economy.py
ars/covenant_integration.py
ars/data/characters/integrus_of_bonisagus.yml
ars/data/covenants/integration_test_covenant.yml
ars/data/laboratories/integrus_of_bonisagus_lab.yml
ars/data/sagas/test saga.yml
ars/dice.py
ars/display.py
ars/faces.py
ars/lab_activities.py
ars/lab_display.py
ars/laboratory.py
ars/magic_items.py
ars/magic_items_integration.py
ars/seasonal_mechanics.py
ars/seasons.py
ars/seasons_integration.py
ars/spell_research.py
ars/spell_research_manager.py
ars/spells.py
ars/types.py
ars/virtues_flaws.py
ars/vis_aura.py
ars/vis_aura_integration.py
ars_magica-0.1.3.dist-info/LICENSE
ars_magica-0.1.3.dist-info/METADATA
ars_magica-0.1.3.dist-info/WHEEL
ars_magica-0.1.3.dist-info/entry_points.txt
ars_magica-0.1.3.dist-info/RECORD
