Metadata-Version: 2.1
Name: ars-magica
Version: 0.1.3
Summary: A Python implementation of Ars Magica 5th Edition mechanics
License: MIT
Keywords: ars magica,rpg,game
Author: bjornaer
Author-email: max.schulkin@gmail.com
Requires-Python: >=3.10
Classifier: Development Status :: 3 - Alpha
Classifier: Intended Audience :: Developers
Classifier: License :: OSI Approved :: MIT License
Classifier: Programming Language :: Python :: 3
Classifier: Programming Language :: Python :: 3.10
Classifier: Programming Language :: Python :: 3.11
Classifier: Programming Language :: Python :: 3.12
Requires-Dist: click (>=8.0.0)
Requires-Dist: pyyaml (>=6.0)
Requires-Dist: rich (>=10.0.0)
Project-URL: Bug Tracker, https://github.com/bjornaer/ars/issues
Project-URL: Homepage, https://github.com/bjornaer/ars
Project-URL: Repository, https://github.com/bjornaer/ars.git
